{
    "type":  "farmersdelight:cutting",
    "ingredients":  [
                        {
                            "item":  "starcatcher:petaldrift_carp"
                        }
                    ],
    "result":  [
                   {
                       "item":  {
                                    "count":  3,
                                    "id":  "minecraft:pink_petals"
                                }
                   },
                   {
                       "item":  {
                                    "count":  2,
                                    "id":  "starcatcher:fish_bones"
                                }
                   }
               ],
    "tool": {
    "item": "kubejs:couperet"
  }
}
